{
  "comment": "Hand-authored conjugation data for the v2 Learn/Conjugation module (PLAN2 §3.1). Présent and imparfait stems are authored; passé composé and futur proche are derived by gen_conjugation.py (aux/participle, aller + infinitive). Street contractions are rule-derived: tu+vowel → t', je+consonant → j' when je_reduction is true. Persons: je/tu/il/on/vous/ils (il stands for il/elle, ils for ils/elles). NOTE: ils-forms are included here — the conjugation module is where full paradigms enter the curriculum (deviation from the v1 je/tu/il/on/vous spec, flagged for review).",
  "verbs": [
    {
      "infinitive": "être",
      "english": "to be",
      "family": "irregular",
      "tier": 0,
      "rank": 1,
      "aux": "avoir",
      "participle": "été",
      "je_reduction": true,
      "present": { "je": "suis", "tu": "es", "il": "est", "on": "est", "vous": "êtes", "ils": "sont" },
      "imparfait_stem": "ét",
      "street_notes": "je suis → j'suis, often chuis in fast speech; tu es → t'es (near-universal); c'est carries most of the load in real speech."
    },
    {
      "infinitive": "avoir",
      "english": "to have",
      "family": "irregular",
      "tier": 0,
      "rank": 2,
      "aux": "avoir",
      "participle": "eu",
      "je_reduction": false,
      "present": { "je": "ai", "tu": "as", "il": "a", "on": "a", "vous": "avez", "ils": "ont" },
      "imparfait_stem": "av",
      "street_notes": "tu as → t'as (near-universal); il y a → y'a. j'ai stays j'ai."
    },
    {
      "infinitive": "aller",
      "english": "to go",
      "family": "irregular",
      "tier": 0,
      "rank": 3,
      "aux": "être",
      "participle": "allé",
      "je_reduction": true,
      "present": { "je": "vais", "tu": "vas", "il": "va", "on": "va", "vous": "allez", "ils": "vont" },
      "imparfait_stem": "all",
      "street_notes": "je vais → j'vais; ça va is the workhorse. Passé composé with être: je suis allé(e)."
    },
    {
      "infinitive": "faire",
      "english": "to do / to make",
      "family": "irregular",
      "tier": 0,
      "rank": 4,
      "aux": "avoir",
      "participle": "fait",
      "je_reduction": true,
      "present": { "je": "fais", "tu": "fais", "il": "fait", "on": "fait", "vous": "faites", "ils": "font" },
      "imparfait_stem": "fais",
      "street_notes": "je fais → j'fais; tu fais quoi ? is the default question form."
    },
    {
      "infinitive": "vouloir",
      "english": "to want",
      "family": "irregular",
      "tier": 1,
      "rank": 5,
      "aux": "avoir",
      "participle": "voulu",
      "je_reduction": true,
      "present": { "je": "veux", "tu": "veux", "il": "veut", "on": "veut", "vous": "voulez", "ils": "veulent" },
      "imparfait_stem": "voul",
      "street_notes": "je veux → j'veux; tu veux → tu veux (no contraction, consonant)."
    },
    {
      "infinitive": "pouvoir",
      "english": "to be able to / can",
      "family": "irregular",
      "tier": 1,
      "rank": 6,
      "aux": "avoir",
      "participle": "pu",
      "je_reduction": true,
      "present": { "je": "peux", "tu": "peux", "il": "peut", "on": "peut", "vous": "pouvez", "ils": "peuvent" },
      "imparfait_stem": "pouv",
      "street_notes": "je peux → j'peux; 'je peux pas' → 'j'peux pas' is one of the most common street strings."
    },
    {
      "infinitive": "devoir",
      "english": "to have to / must",
      "family": "irregular",
      "tier": 1,
      "rank": 7,
      "aux": "avoir",
      "participle": "dû",
      "je_reduction": true,
      "present": { "je": "dois", "tu": "dois", "il": "doit", "on": "doit", "vous": "devez", "ils": "doivent" },
      "imparfait_stem": "dev",
      "street_notes": "je dois → j'dois."
    },
    {
      "infinitive": "savoir",
      "english": "to know (facts, how to)",
      "family": "irregular",
      "tier": 1,
      "rank": 8,
      "aux": "avoir",
      "participle": "su",
      "je_reduction": true,
      "present": { "je": "sais", "tu": "sais", "il": "sait", "on": "sait", "vous": "savez", "ils": "savent" },
      "imparfait_stem": "sav",
      "street_notes": "je sais pas → j'sais pas → chais pas (the app's namesake)."
    },
    {
      "infinitive": "dire",
      "english": "to say / to tell",
      "family": "irregular",
      "tier": 1,
      "rank": 9,
      "aux": "avoir",
      "participle": "dit",
      "je_reduction": true,
      "present": { "je": "dis", "tu": "dis", "il": "dit", "on": "dit", "vous": "dites", "ils": "disent" },
      "imparfait_stem": "dis",
      "street_notes": "je dis → j'dis; on dit for general statements."
    },
    {
      "infinitive": "voir",
      "english": "to see",
      "family": "irregular",
      "tier": 1,
      "rank": 10,
      "aux": "avoir",
      "participle": "vu",
      "je_reduction": true,
      "present": { "je": "vois", "tu": "vois", "il": "voit", "on": "voit", "vous": "voyez", "ils": "voient" },
      "imparfait_stem": "voy",
      "street_notes": "je vois → j'vois; tu vois as a filler ('you know')."
    },
    {
      "infinitive": "prendre",
      "english": "to take",
      "family": "irregular",
      "tier": 2,
      "rank": 11,
      "aux": "avoir",
      "participle": "pris",
      "je_reduction": true,
      "present": { "je": "prends", "tu": "prends", "il": "prend", "on": "prend", "vous": "prenez", "ils": "prennent" },
      "imparfait_stem": "pren",
      "street_notes": "je prends → j'prends; the café-order verb: je prends un café."
    },
    {
      "infinitive": "venir",
      "english": "to come",
      "family": "irregular",
      "tier": 2,
      "rank": 12,
      "aux": "être",
      "participle": "venu",
      "je_reduction": true,
      "present": { "je": "viens", "tu": "viens", "il": "vient", "on": "vient", "vous": "venez", "ils": "viennent" },
      "imparfait_stem": "ven",
      "street_notes": "je viens → j'viens; tu viens ? as a one-word invitation. Passé composé with être."
    },
    {
      "infinitive": "mettre",
      "english": "to put / to put on",
      "family": "irregular",
      "tier": 2,
      "rank": 13,
      "aux": "avoir",
      "participle": "mis",
      "je_reduction": true,
      "present": { "je": "mets", "tu": "mets", "il": "met", "on": "met", "vous": "mettez", "ils": "mettent" },
      "imparfait_stem": "mett",
      "street_notes": "je mets → j'mets."
    },
    {
      "infinitive": "parler",
      "english": "to speak / to talk",
      "family": "er_regular",
      "tier": 2,
      "rank": 14,
      "aux": "avoir",
      "participle": "parlé",
      "je_reduction": false,
      "present": { "je": "parle", "tu": "parles", "il": "parle", "on": "parle", "vous": "parlez", "ils": "parlent" },
      "imparfait_stem": "parl",
      "street_notes": "The model -er verb: one spoken form for je/tu/il/on/ils (parle/parles/parlent all sound identical)."
    },
    {
      "infinitive": "aimer",
      "english": "to like / to love",
      "family": "er_regular",
      "tier": 2,
      "rank": 15,
      "aux": "avoir",
      "participle": "aimé",
      "je_reduction": false,
      "present": { "je": "aime", "tu": "aimes", "il": "aime", "on": "aime", "vous": "aimez", "ils": "aiment" },
      "imparfait_stem": "aim",
      "street_notes": "j'aime is elision, not slang — it's the only correct form. j'aime bien = I like (softer than j'aime)."
    },
    {
      "infinitive": "acheter",
      "english": "to buy",
      "family": "er_regular",
      "tier": 3,
      "rank": 16,
      "aux": "avoir",
      "participle": "acheté",
      "je_reduction": false,
      "present": { "je": "achète", "tu": "achètes", "il": "achète", "on": "achète", "vous": "achetez", "ils": "achètent" },
      "imparfait_stem": "achet",
      "street_notes": "Stem-change -er verb: è in the singular/ils forms (j'achète), plain e when the ending is pronounced (vous achetez)."
    },
    {
      "infinitive": "manger",
      "english": "to eat",
      "family": "er_regular",
      "tier": 3,
      "rank": 17,
      "aux": "avoir",
      "participle": "mangé",
      "je_reduction": false,
      "present": { "je": "mange", "tu": "manges", "il": "mange", "on": "mange", "vous": "mangez", "ils": "mangent" },
      "imparfait_stem": "mange",
      "street_notes": "on mange ? as an invitation. Imparfait keeps the e: je mangeais."
    },
    {
      "infinitive": "partir",
      "english": "to leave",
      "family": "irregular",
      "tier": 3,
      "rank": 18,
      "aux": "être",
      "participle": "parti",
      "je_reduction": true,
      "present": { "je": "pars", "tu": "pars", "il": "part", "on": "part", "vous": "partez", "ils": "partent" },
      "imparfait_stem": "part",
      "street_notes": "je pars → j'pars; on part ? = shall we go? Passé composé with être: je suis parti(e)."
    },
    {
      "infinitive": "finir",
      "english": "to finish",
      "family": "ir_regular",
      "tier": 3,
      "rank": 19,
      "aux": "avoir",
      "participle": "fini",
      "je_reduction": false,
      "present": { "je": "finis", "tu": "finis", "il": "finit", "on": "finit", "vous": "finissez", "ils": "finissent" },
      "imparfait_stem": "finiss",
      "street_notes": "The model regular -ir verb (-iss- in plural forms). c'est fini = it's over."
    },
    {
      "infinitive": "donner",
      "english": "to give",
      "family": "er_regular",
      "tier": 3,
      "rank": 20,
      "aux": "avoir",
      "participle": "donné",
      "je_reduction": false,
      "present": { "je": "donne", "tu": "donnes", "il": "donne", "on": "donne", "vous": "donnez", "ils": "donnent" },
      "imparfait_stem": "donn",
      "street_notes": "donne-moi = give me (imperative preview); ça donne quoi ? = how's it going / what's it like?"
    }
  ],
  "politesse": {
    "id": "conj_politesse_conditionnel",
    "title": "Politeness conditionals: je voudrais, je pourrais, il faudrait",
    "tier": 2,
    "prereq_ids": ["conditional_softeners"],
    "comment": "Mini-module per PLAN2 §3.1. Deepens the v1 conditional_softeners node — fixed high-value phrases, not a full conditional paradigm.",
    "forms": [
      { "id": "f01", "formal": "je voudrais", "street": "je voudrais", "english": "I would like" },
      { "id": "f02", "formal": "j'aimerais", "street": "j'aimerais", "english": "I would love / I'd like" },
      { "id": "f03", "formal": "je pourrais", "street": "j'pourrais", "english": "I could" },
      { "id": "f04", "formal": "tu pourrais", "street": "tu pourrais", "english": "you could (informal)" },
      { "id": "f05", "formal": "vous pourriez", "street": "vous pourriez", "english": "you could (formal)" },
      { "id": "f06", "formal": "il faudrait", "street": "faudrait", "english": "we/one would need to" },
      { "id": "f07", "formal": "ce serait", "street": "ça serait", "english": "it would be" }
    ]
  }
}
